[
  {
    "id": "1",
    "name": "Custom Name Keychain",
    "category": "Gifts",
    "price": 149,
    "rating": 4.8,
    "reviews": 124,
    "image": "/images/custom-gifts.jpg",
    "badge": "Best Seller",
    "description": "Personalized keychain with your name or logo",
    "fullDesc": "Fully customizable keychain printed in durable PLA. Choose your name, initials, or a short message. Available in 10+ colors. Perfect for gifting or corporate branding. Each piece is sanded and finished for a smooth feel.",
    "material": "PLA",
    "dimensions": "6cm × 2cm × 0.4cm",
    "printTime": "45 minutes",
    "tags": ["Personalized", "Gift", "PLA"],
    "active": true,
    "createdAt": "2024-01-01T00:00:00.000Z"
  },
  {
    "id": "2",
    "name": "Miniature Building Model",
    "category": "Architectural",
    "price": 2499,
    "rating": 4.9,
    "reviews": 38,
    "image": "/images/architectural-miniature.jpg",
    "badge": "Premium",
    "description": "Detailed scale model of any building or structure",
    "fullDesc": "High-detail architectural scale models built from your blueprints or reference images. Ideal for real estate presentations, urban planning, and exhibitions. Printed in multiple parts and assembled with precision. Custom scale available on request.",
    "material": "PLA + Resin",
    "dimensions": "Custom (up to 30cm × 30cm)",
    "printTime": "12–48 hours",
    "tags": ["Architecture", "Scale Model", "Custom"],
    "active": true,
    "createdAt": "2024-01-02T00:00:00.000Z"
  },
  {
    "id": "3",
    "name": "Desk Organizer Set",
    "category": "Home Decor",
    "price": 599,
    "rating": 4.6,
    "reviews": 87,
    "image": "/images/3d-printer.jpg",
    "badge": "",
    "description": "Modular desk organizer for pens, cards, and accessories",
    "fullDesc": "A modular 3-piece desk organizer set designed for clean, minimal workspaces. Holds pens, business cards, sticky notes, and small accessories. Printed in matte finish PLA. Available in white, black, and grey.",
    "material": "PLA",
    "dimensions": "20cm × 10cm × 8cm",
    "printTime": "3 hours",
    "tags": ["Home", "Organizer", "Minimal"],
    "active": true,
    "createdAt": "2024-01-03T00:00:00.000Z"
  },
  {
    "id": "4",
    "name": "Functional Gear Assembly",
    "category": "Industrial",
    "price": 1299,
    "rating": 4.7,
    "reviews": 52,
    "image": "/images/prototyping.jpg",
    "badge": "New",
    "description": "Custom gear sets and mechanical assemblies",
    "fullDesc": "Precision-printed gear assemblies for prototyping and light industrial use. Printed in PETG for strength and heat resistance. Custom tooth profiles, module sizes, and shaft diameters available. Ideal for robotics, automation, and educational projects.",
    "material": "PETG / Nylon",
    "dimensions": "Custom",
    "printTime": "2–6 hours",
    "tags": ["Industrial", "Mechanical", "PETG"],
    "active": true,
    "createdAt": "2024-01-04T00:00:00.000Z"
  },
  {
    "id": "5",
    "name": "Character Figurine",
    "category": "Figurines",
    "price": 899,
    "rating": 4.9,
    "reviews": 201,
    "image": "/images/custom-gifts.jpg",
    "badge": "Best Seller",
    "description": "Custom 3D printed figurine from your design or photo",
    "fullDesc": "Turn your character design, game avatar, or photo into a detailed 3D figurine. Printed in high-resolution resin for fine detail. Available in 10cm, 15cm, and 20cm heights. Delivered primed and ready to paint, or fully painted on request.",
    "material": "Resin",
    "dimensions": "10cm / 15cm / 20cm height",
    "printTime": "4–8 hours",
    "tags": ["Figurine", "Resin", "Custom"],
    "active": true,
    "createdAt": "2024-01-05T00:00:00.000Z"
  },
  {
    "id": "6",
    "name": "Solar System Model",
    "category": "Educational",
    "price": 1099,
    "rating": 4.8,
    "reviews": 63,
    "image": "/images/3d-printed-models.jpg",
    "badge": "",
    "description": "Detailed scale model of the solar system for classrooms",
    "fullDesc": "An accurate scale model of the solar system with all 8 planets and the sun. Each planet is labeled and color-coded. Comes with a display stand. Great for schools, science fairs, and home learning. Printed in PLA with vibrant colors.",
    "material": "PLA",
    "dimensions": "Base: 40cm × 10cm",
    "printTime": "8 hours",
    "tags": ["Education", "Science", "Display"],
    "active": true,
    "createdAt": "2024-01-06T00:00:00.000Z"
  },
  {
    "id": "7",
    "name": "Planter Pot Set",
    "category": "Home Decor",
    "price": 449,
    "rating": 4.5,
    "reviews": 109,
    "image": "/images/bulk-manufacturing.jpg",
    "badge": "",
    "description": "Geometric planter pots for succulents and small plants",
    "fullDesc": "A set of 3 geometric planter pots in different sizes. Designed with drainage holes and a matching tray. Printed in weather-resistant PETG. Suitable for indoor and outdoor use. Available in terracotta, white, and charcoal.",
    "material": "PETG",
    "dimensions": "S: 8cm, M: 12cm, L: 16cm diameter",
    "printTime": "5 hours",
    "tags": ["Home", "Plants", "Geometric"],
    "active": true,
    "createdAt": "2024-01-07T00:00:00.000Z"
  },
  {
    "id": "8",
    "name": "Trophy & Award",
    "category": "Gifts",
    "price": 799,
    "rating": 4.7,
    "reviews": 76,
    "image": "/images/custom-gifts.jpg",
    "badge": "New",
    "description": "Custom trophy with name, logo, and achievement text",
    "fullDesc": "Fully customizable trophy for sports, corporate events, and competitions. Add a name, logo, date, and achievement text. Printed in gold or silver PLA with a weighted base for stability. Available in 3 sizes.",
    "material": "PLA (metallic finish)",
    "dimensions": "15cm / 20cm / 25cm height",
    "printTime": "3–5 hours",
    "tags": ["Trophy", "Award", "Corporate"],
    "active": true,
    "createdAt": "2024-01-08T00:00:00.000Z"
  },
  {
    "id": "9",
    "name": "Prototype Enclosure",
    "category": "Industrial",
    "price": 1799,
    "rating": 4.6,
    "reviews": 44,
    "image": "/images/prototyping.jpg",
    "badge": "",
    "description": "Custom enclosures for electronics and PCB projects",
    "fullDesc": "Custom-designed enclosures for Arduino, Raspberry Pi, and other electronics projects. Printed in ABS for heat resistance. Includes cutouts for ports, buttons, and displays as per your design. Snap-fit or screw-mount assembly options available.",
    "material": "ABS",
    "dimensions": "Custom",
    "printTime": "3–8 hours",
    "tags": ["Electronics", "Enclosure", "ABS"],
    "active": true,
    "createdAt": "2024-01-09T00:00:00.000Z"
  }
]
